first_llm_rag/core/data_process.cpython-310-x86_64-linux-gnu.so
first_llm_rag/core/prompts.cpython-310-x86_64-linux-gnu.so
first_llm_rag/core/vec_store.cpython-310-x86_64-linux-gnu.so
first_llm_rag-0.1.1.dist-info/METADATA
first_llm_rag-0.1.1.dist-info/WHEEL
first_llm_rag-0.1.1.dist-info/top_level.txt
first_llm_rag-0.1.1.dist-info/RECORD
