Metadata-Version: 2.4
Name: first_llm_rag
Version: 0.1.1
Summary: My tiny package
Author-email: YKP <ykp0613@163.com>
License: MIT
Keywords: hello,example
Classifier: Programming Language :: Python :: 3
Classifier: License :: OSI Approved :: MIT License
Classifier: Operating System :: OS Independent
Requires-Python: >=3.10
